scm_python_edu/lib/edu.py
scm_python_edu/tapps/edu/common.py
scm_python_edu/tapps/edu/disjunction.py
scm_python_edu/tapps/edu/fraction.py
scm_python_edu/tapps/edu/latex.py
scm_python_edu/tapps/edu/math.py
scm_python_edu/tapps/edu/withFraction.py
scm_python_edu-0.1.0.dist-info/METADATA
scm_python_edu-0.1.0.dist-info/WHEEL
scm_python_edu-0.1.0.dist-info/top_level.txt
scm_python_edu-0.1.0.dist-info/RECORD
